src/__init__.py
src/paranoid.py
src/timestamp_validator_27.py
src/timestamp_validator_3.py
src/version.py
PARANOID-1.2.9.dist-info/LICENSE
PARANOID-1.2.9.dist-info/METADATA
PARANOID-1.2.9.dist-info/WHEEL
PARANOID-1.2.9.dist-info/entry_points.txt
PARANOID-1.2.9.dist-info/top_level.txt
PARANOID-1.2.9.dist-info/RECORD
