Metadata-Version: 2.1
Name: PARANOID
Version: 1.2.9
Summary: A utility to obfuscate and mask elements in XML and JSON files
Home-page: https://gitlab.com/sonra-labs/paranoid
Author: Sonra Intelligence Ltd
Author-email: hello@sonra.io
License: Apache Software License
Platform: UNKNOWN
Classifier: Programming Language :: Python
Classifier: Programming Language :: Python :: 2
Classifier: Programming Language :: Python :: 2.7
Classifier: Programming Language :: Python :: 3
Classifier: Programming Language :: Python :: 3.4
Classifier: Programming Language :: Python :: 3.5
Classifier: Programming Language :: Python :: 3.6
Classifier: Programming Language :: Python :: 3.7
Classifier: Operating System :: OS Independent
Classifier: License :: OSI Approved :: Apache Software License
Requires-Python: >=2.6, >=2.6.*,>=2.7.*, <4
